<?xml version="1.0" encoding="UTF-8"?>
<blogs>
    <blog>
        <id>1</id>
        <title>First Blog Post</title>
        <author>Author 1</author>
        <date>2024-10-30</date>
        <category>Technology</category>
        <content>This is the content of the first blog post.</content>
        <image>https://i.pinimg.com/736x/bb/4a/6d/bb4a6d17f7c4334697ad7ac008018789.jpg</image>
    </blog>
    <blog>
        <id>2</id>
        <title>Second Blog Post</title>
        <author>Author 2</author>
        <date>2024-10-31</date>
        <category>Science</category>
        <content>This is the content of the second blog post.</content>
        <image>http://example.com/image2.jpg</image>
    </blog>
    <blog>
        <id>3</id>
        <title>Web Development: Skills, Technologies, and Trends in 2024</title>
        <author>Your Name</author>
        <date>2024-10-30</date>
        <category>Web Development</category>
        <content><![CDATA[
            <p>Web development skills are in high demand and offer a pathway to numerous career opportunities. Plus, creating something that others can see and use is deeply satisfying. It’s a versatile skill that allows you to work on everything from personal projects to professional websites for businesses.</p>
            <h2 class="text-2xl font-semibold mb-3">Key Technologies and Trends in 2024</h2>
            <p class="mb-4">The trends shaping web development in 2024 include advancements in AI integration, WebAssembly, responsive design improvements, and enhanced security protocols. Learning these technologies will give developers an edge in the ever-competitive tech industry.</p>
            <p class="mb-4">As we dive deeper, tutorials, tips, and tricks will help you become a successful web developer. Whether you're interested in frontend, backend, or full-stack development, these skills will help you build something amazing.</p>
        ]]></content>
        <image>https://i.pinimg.com/736x/e2/35/d7/e235d7aa023d0c03310caeb2998daece.jpg</image>
    </blog>
</blogs>
